fsim/sgmii.v
module mii_sgmii (
    //module reset
    rst_l, 
    
    //sgmii rx/tx
    tx,
    rx, 

    //mii interface 
    mii_rxclk, 
    mii_rxd, 
    mii_rx_dv, 
    mii_rx_er, 
    mii_rx_crs, 
    mii_rx_col,

    mii_txclk, 
    mii_txd,
    mii_tx_en, 
    mii_tx_er
    );

    //module reset
input rst_l; 
    
    //sgmii rx/tx
output tx;
input rx; 

    //mii interface 
input mii_rxclk; 
output [3:0] mii_rxd; 
output mii_rx_dv; 
output mii_rx_er; 
output mii_rx_crs; 
output mii_rx_col;

input mii_txclk; 
input [3:0] mii_txd;
input mii_tx_en; 
input mii_tx_er;
/*
//interal regs and wires
wire [8:0] DataFromEnc; 
reg  [8:0] DataFromEnc_r; 
reg  [8:0] DataToEnc_r; 
reg enc_clk; 

wire [9:0] EncodedDataIn;
wire [9:0] EncodedDataOut;
reg  [9:0] EncodedDataOut_r;

//generate clock running half the frequency of mii clock 
//shift mii data into 8 bit reg 
always @ (posedge(mii_txclk),rst_l) begin 
    if(rst_l == 1'b0) begin 
        enc_clk = 1'b0;
        DataToEnc_r = 9'b000000000; 
    end
    else if(mii_txclk == 1'b1) begin 
        enc_clk = !enc_clk; 
        DataToEnc_r[8]   = 1'b0;
        DataToEnc_r[7:4] = DataToEnc_r[3:0]; 
        DataToEnc_r[3:0] = mii_txd;
    end
end 

//8b10b encode and decode modules
wire Encode_disp;
reg  Encode_disp_r;
encode encode_8b10b 
(
    .datain(DataToEnc_r), 
    .dispin(Encode_disp_r),
    .dataout(EncodedDataOut), 
    .dispout(Encode_disp)
);

//register output of encoded data 
always @ (posedge(enc_clk),rst_l) begin 
    if(rst_l == 1'b0) begin 
        EncodedDataOut_r = 10'b0000000000;
        Encode_disp_r = 1'b0; 
    end
    else if (enc_clk == 1'b1) begin 
        EncodedDataOut_r = EncodedDataOut; 
        Encode_disp_r = Encode_disp; 
    end
end

wire Decode_disp;
reg  Decode_disp_r;
reg  code_err_r;
wire code_err;
reg  disp_err_r; 
wire disp_err; 

decode decode_8b10b 
(
    .datain(EncodedDataIn),
    .dispin(Decode_disp_r),
    .dataout(DataFromEnc),
    .dispout(Decode_disp), 
    .code_err(code_err),
    .disp_err(disp_err)
);

always @ (posedge(enc_clk),rst_l) begin 
    if(rst_l == 1'b0) begin 
        DataFromEnc_r = 9'b000000000;
        Decode_disp_r = 1'b0;
        code_err_r    = 1'b0;
        disp_err_r    = 1'b0;
    end
    else if (enc_clk == 1'b1) begin 
        DataFromEnc_r = DataFromEnc; 
        Decode_disp_r = Decode_disp; 
        code_err_r    = code_err; 
        disp_err_r    = disp_err; 
    end
end

assign EncodedDataIn = EncodedDataOut_r; 

//convert decoded 8 bit data to mii data
reg nib;
reg [3:0] mii_out; 
always @ (posedge(mii_txclk),rst_l) begin 
    if(rst_l == 1'b0 ) begin 
        nib = 1'b0;
        mii_out = 4'b0000; 
    end
    else if (mii_txclk == 1'b1) begin 
        if(nib == 1'b0) begin
            mii_out = DataFromEnc_r[3:0];
            nib = 1'b1; 
        end
        else begin 
            mii_out = DataFromEnc_r[7:4];
            nib = 1'b0;
        end
    end 
end

assign mii_rxd    = mii_out; 
assign mii_rx_dv  = 1'b1;
assign mii_rx_crs = 1'b1;
assign mii_rx_er  = 1'b0;
assign mii_rx_col = 1'b0;

/*/
assign mii_rx_dv  = mii_tx_en; 
assign mii_rx_crs = mii_tx_en;

assign mii_rxd = mii_txd; 

assign mii_rx_er = 1'b0; 
assign mii_rx_col = 1'b0;

endmodule

fsim/rmii_mii.v
`timescale 1ps/1ps

module rmii_mii(
    //rmii
    rmii_refclk,
    rst_l,

    rmii_txd,
    rmii_tx_en,

    rmii_rx_er,
    rmii_crs_dv,
    rmii_rxd,

    //mii
    mii_rxclk,
    mii_rxd,
    mii_rx_dv,
    mii_rx_er,
    mii_crs,
    mii_col,

    mii_txclk,
    mii_txd,
    mii_tx_en,
    mii_tx_er

);

//rmii interface
input rmii_refclk;
input rst_l;

input [1:0] rmii_txd;
input rmii_tx_en;

output rmii_rx_er;
output rmii_crs_dv;
output [1:0] rmii_rxd;

//mii interface
input mii_rxclk;
input [3:0] mii_rxd;
input mii_rx_dv;
input mii_rx_er;
input mii_crs;
input mii_col;

input mii_txclk;
output [3:0] mii_txd;
output mii_tx_en;
output mii_tx_er;


//internal signals
reg [3:0] mii_data_rx_r1;
reg [3:0] mii_data_rx_r2;
reg [1:0] rmii_data_rx_r1;
reg nib;

reg mii_crs_r1;
reg mii_crs_r2;
reg mii_rx_dv_r1;
reg mii_rx_dv_r2;
reg rmii_crs_dv_r1;

reg mii_rx_er_r1;
reg mii_rx_er_r2;
reg rmii_rx_er_r1;


reg [3:0] mii_data_tx_r1;
reg [3:0] mii_data_tx_r2;
reg [3:0] mii_data_tx_r3;
reg mii_tx_en_r1;
reg mii_tx_en_r2;
reg mii_tx_en_r3;

reg mii_clk_rx_r;
reg crs_dv_r;

// -------------------------- RMII/MII Transmit Path --------------------- \\
//rmii to mii (tx)
always @ (posedge(rmii_refclk)) begin
    if(rst_l == 1'b0) begin
        mii_data_tx_r1 <= 4'b0000;
        mii_tx_en_r1   <= 1'b0;
    end

    else if(rmii_refclk == 1'b1) begin
        mii_data_tx_r1[1:0] <= mii_data_tx_r1[3:2];
        mii_data_tx_r1[3:2] <= rmii_txd;
        mii_tx_en_r1 <= rmii_tx_en;
    end
end

//sync mii to mii tx_clk domain
always @ (posedge(mii_txclk)) begin
    if(rst_l == 1'b0) begin
        mii_data_tx_r2 <= 4'b0000;
        mii_data_tx_r3 <= 4'b0000;

        mii_tx_en_r2   <= 1'b0;
        mii_tx_en_r3   <= 1'b0;
    end

    if(mii_txclk == 1'b1) begin
        mii_data_tx_r2 <= mii_data_tx_r1;
        mii_data_tx_r3 <= mii_data_tx_r2;

        mii_tx_en_r2   <= mii_tx_en_r1;
        mii_tx_en_r3   <= mii_tx_en_r2;
    end

end

assign mii_txd   = mii_data_tx_r3;
assign mii_tx_en = mii_tx_en_r3;

// -------------------------- RMII/MII Receive Path --------------------- \\
//sync mii rx signals to rmii rx clock domain
always @ (posedge(rmii_refclk)) begin
    if(rst_l == 1'b0) begin
        mii_data_rx_r1 <= 4'b0000;
        mii_data_rx_r2 <= 4'b0000;
        mii_crs_r1 <= 1'b0;
        mii_crs_r2 <= 1'b0;

        mii_rx_dv_r1 <= 1'b0;
        mii_rx_dv_r2 <= 1'b0;

        mii_rx_er_r1 <= 1'b0;
        mii_rx_er_r2 <= 1'b0;
    end

    else if (rmii_refclk == 1'b1) begin
        mii_data_rx_r1 <= mii_rxd;
        mii_data_rx_r2 <= mii_data_rx_r1;

        mii_crs_r1 <= mii_crs;
        mii_crs_r2 <= mii_crs_r1;

        mii_rx_dv_r1 <= mii_rx_dv;
        mii_rx_dv_r2 <= mii_rx_dv_r1;

        mii_rx_er_r1 <= mii_rx_er;
        mii_rx_er_r2 <= mii_rx_er_r1;
    end
end

//convert synced mii data to rmii data
always @ (posedge(rmii_refclk)) begin
    if(rst_l == 1'b0) begin
        rmii_data_rx_r1 <= 2'b00;
        rmii_crs_dv_r1  <= 1'b0;
        rmii_rx_er_r1   <= 1'b0;
        nib <= 1'b0;
    end
    else if (rmii_refclk == 1'b1) begin
        if(nib == 1'b0) begin
            rmii_data_rx_r1[1:0] <= mii_data_rx_r2[3:2];
            nib <= 1;
        end
        else begin
            rmii_data_rx_r1[1:0] <= mii_data_rx_r2[1:0];
            nib <= 0;
        end
        rmii_crs_dv_r1 <= (mii_crs_r2 | mii_rx_dv_r2);
        rmii_rx_er_r1  <= mii_rx_er_r2;
    end
end

assign rmii_rxd    = rmii_data_rx_r1;
assign rmii_crs_dv = rmii_crs_dv_r1;
assign rmii_rx_er  = rmii_rx_er_r1;

endmodule

fsim/top.v
`timescale 1ps/1ps

module top (
    rst_l,
    sgmii_tx, 
    sgmii_rx,

    mii_clk,
    rmii_refclk, 
    rmii_txd,
    rmii_tx_en,
    rmii_rx_er,
    rmii_crs_dv,
    rmii_rxd

    );

input rst_l;
output sgmii_tx;
input  sgmii_rx; 
input mii_clk; 
input rmii_refclk;
input [1:0] rmii_txd;
input rmii_tx_en;


output rmii_rx_er;
output rmii_crs_dv;
output [1:0] rmii_rxd; 



//internal wires
wire mii_rx_dv;
wire mii_rx_er;
wire mii_rx_crs;
wire mii_rx_col;
wire [3:0] mii_rxd;

wire [3:0] mii_txd;
wire mii_tx_en;
wire mii_tx_er;

rmii_mii rmii_conv
(   
    //rmii 
    .rmii_refclk (rmii_refclk), 
    .rst_l       (rst_l),
    
    .rmii_txd    (rmii_txd),
    .rmii_tx_en  (rmii_tx_en),

    .rmii_rx_er  (rmii_rx_er),
    .rmii_crs_dv (rmii_crs_dv),
    .rmii_rxd    (rmii_rxd),

    //mii 
    .mii_rxclk   (mii_clk),
    .mii_rxd     (mii_rxd),
    .mii_rx_dv   (mii_rx_dv),
    .mii_rx_er   (mii_rx_er),
    .mii_crs     (mii_rx_crs),
    .mii_col     (mii_rx_col), 

    .mii_txclk   (mii_clk), 
    .mii_txd     (mii_txd),
    .mii_tx_en   (mii_tx_en), 
    .mii_tx_er   (mii_tx_er)
);

mii_sgmii sgmii
(
    .rst_l(rst_l),
    .tx(sgmii_tx),
    .rx(sgmii_rx), 
    .mii_rxclk(mii_clk),
    .mii_rxd(mii_rxd),
    .mii_rx_dv(mii_rx_dv),
    .mii_rx_er(mii_rx_er),
    .mii_rx_crs(mii_rx_crs),
    .mii_rx_col(mii_rx_col),

    .mii_txclk(mii_clk), 
    .mii_txd(mii_txd),
    .mii_tx_en(mii_tx_en),
    .mii_tx_er(mii_tx_er)
);

//`ifdef COCOTB_SIM 
initial begin 
  $dumpfile ("waveform.vcd"); 
  $dumpvars (0,top);   
  #1; 
end 
//`endif 

endmodule

fsim/waveform.vcd
$date
	Wed Feb 22 16:13:01 2017
$end
$version
	Icarus Verilog
$end
$timescale
	1ps
$end
$scope module top $end
$var wire 1 ! mii_clk $end
$var wire 1 " mii_rx_col $end
$var wire 1 # mii_rx_crs $end
$var wire 1 $ mii_rx_dv $end
$var wire 1 % mii_rx_er $end
$var wire 4 & mii_rxd [3:0] $end
$var wire 1 ' mii_tx_en $end
$var wire 1 ( mii_tx_er $end
$var wire 4 ) mii_txd [3:0] $end
$var wire 1 * rmii_crs_dv $end
$var wire 1 + rmii_refclk $end
$var wire 1 , rmii_rx_er $end
$var wire 2 - rmii_rxd [1:0] $end
$var wire 1 . rmii_tx_en $end
$var wire 2 / rmii_txd [1:0] $end
$var wire 1 0 rst_l $end
$var wire 1 1 sgmii_rx $end
$var wire 1 2 sgmii_tx $end
$scope module rmii_conv $end
$var wire 1 " mii_col $end
$var wire 1 # mii_crs $end
$var wire 1 $ mii_rx_dv $end
$var wire 1 % mii_rx_er $end
$var wire 1 ! mii_rxclk $end
$var wire 4 3 mii_rxd [3:0] $end
$var wire 1 ' mii_tx_en $end
$var wire 1 ( mii_tx_er $end
$var wire 1 ! mii_txclk $end
$var wire 4 4 mii_txd [3:0] $end
$var wire 1 * rmii_crs_dv $end
$var wire 1 + rmii_refclk $end
$var wire 1 , rmii_rx_er $end
$var wire 2 5 rmii_rxd [1:0] $end
$var wire 1 . rmii_tx_en $end
$var wire 2 6 rmii_txd [1:0] $end
$var wire 1 0 rst_l $end
$var reg 1 7 mii_crs_r1 $end
$var reg 1 8 mii_crs_r2 $end
$var reg 4 9 mii_data_rx_r1 [3:0] $end
$var reg 4 : mii_data_rx_r2 [3:0] $end
$var reg 4 ; mii_data_tx_r1 [3:0] $end
$var reg 4 < mii_data_tx_r2 [3:0] $end
$var reg 4 = mii_data_tx_r3 [3:0] $end
$var reg 1 > mii_rx_dv_r1 $end
$var reg 1 ? mii_rx_dv_r2 $end
$var reg 1 @ mii_rx_er_r1 $end
$var reg 1 A mii_rx_er_r2 $end
$var reg 1 B mii_tx_en_r1 $end
$var reg 1 C mii_tx_en_r2 $end
$var reg 1 D mii_tx_en_r3 $end
$var reg 1 E nib $end
$var reg 1 F rmii_crs_dv_r1 $end
$var reg 2 G rmii_data_rx_r1 [1:0] $end
$var reg 1 H rmii_rx_er_r1 $end
$upscope $end
$scope module sgmii $end
$var wire 1 " mii_rx_col $end
$var wire 1 # mii_rx_crs $end
$var wire 1 $ mii_rx_dv $end
$var wire 1 % mii_rx_er $end
$var wire 1 ! mii_rxclk $end
$var wire 4 I mii_rxd [3:0] $end
$var wire 1 ' mii_tx_en $end
$var wire 1 ( mii_tx_er $end
$var wire 1 ! mii_txclk $end
$var wire 4 J mii_txd [3:0] $end
$var wire 1 0 rst_l $end
$var wire 1 1 rx $end
$var wire 1 2 tx $end
$upscope $end
$upscope $end
$enddefinitions $end
#0
$dumpvars
bx J
bx I
xH
bx G
xF
xE
xD
xC
xB
xA
x@
x?
x>
bx =
bx <
bx ;
bx :
bx 9
x8
x7
b0 6
bx 5
bx 4
bx 3
z2
z1
00
b0 /
0.
bx -
x,
0+
x*
bx )
z(
x'
bx &
0%
x$
x#
0"
z!
$end
#10000
0!
#20000
0B
b0 ;
0A
0@
0?
0>
08
07
b0 :
b0 9
0E
0H
0,
0F
0*
b0 G
b0 -
b0 5
1+
#30000
0D
0$
0#
0'
0C
b0 =
b0 &
b0 3
b0 I
b0 )
b0 4
b0 J
b0 <
0+
1!
#40000
1+
#50000
0+
0!
#60000
1+
#70000
0+
1!
#80000
1+
#90000
0+
0!
10
#100000
b0 ;
1E
1+
#110000
1!
0+
b1 /
b1 6
1.
#120000
0E
1B
b1 ;
1+
#130000
0+
0!
#140000
b101 ;
1E
1+
#150000
1D
1$
1#
1'
1C
b101 =
b101 &
b101 3
b101 I
b101 )
b101 4
b101 J
b101 <
0+
1!
#160000
1F
1*
0E
b1 G
b1 -
b1 5
1?
1>
18
17
b101 :
b101 9
b101 ;
1+
#170000
0+
0!
#180000
b101 ;
1E
1+
#190000
0+
1!
#200000
0E
b101 ;
1+
#210000
0+
0!
#220000
b101 ;
1E
1+
#230000
0+
1!
#240000
0E
b101 ;
1+
#250000
0+
0!
#260000
b101 ;
1E
1+
#270000
0+
1!
#280000
0E
b101 ;
1+
#290000
0+
0!
#300000
b101 ;
1E
1+
#310000
0+
1!
#320000
0E
b101 ;
1+
#330000
0+
0!
#340000
b101 ;
1E
1+
#350000
0+
1!
#360000
0E
b101 ;
1+
#370000
0+
0!
#380000
b101 ;
1E
1+
#390000
0+
1!
#400000
0E
b101 ;
1+
#410000
0+
0!
#420000
b101 ;
1E
1+
#430000
0+
1!
#440000
0E
b101 ;
1+
#450000
0+
0!
#460000
b101 ;
1E
1+
#470000
0+
1!
#480000
0E
b101 ;
1+
#490000
0+
0!
#500000
b101 ;
1E
1+
#510000
0+
1!
#520000
0E
b101 ;
1+
#530000
0+
0!
#540000
b101 ;
1E
1+
#550000
0+
1!
#560000
0E
b101 ;
1+
#570000
0+
0!
#580000
b101 ;
1E
1+
#590000
0+
1!
#600000
0E
b101 ;
1+
#610000
0+
0!
#620000
b101 ;
1E
1+
#630000
0+
1!
#640000
0E
b101 ;
1+
#650000
0+
0!
#660000
b101 ;
1E
1+
#670000
0+
1!
#680000
0E
b101 ;
1+
#690000
0+
0!
#700000
b101 ;
1E
1+
#710000
0+
1!
#720000
b11 /
b11 6
0E
b101 ;
1+
#730000
0+
0!
#740000
b10 /
b10 6
b111 ;
1E
1+
#750000
b111 =
b111 &
b111 3
b111 I
b111 )
b111 4
b111 J
b111 <
0+
1!
#760000
b1 /
b1 6
0E
b111 :
b111 9
b1110 ;
1+
#770000
0+
0!
#780000
b11 /
b11 6
b1001 ;
1E
b11 G
b11 -
b11 5
1+
#790000
b1001 =
b1001 &
b1001 3
b1001 I
b1001 )
b1001 4
b1001 J
b1001 <
0+
1!
#800000
0E
b10 G
b10 -
b10 5
b1001 :
b1001 9
b111 ;
1+
#810000
0+
0!
#820000
b1111 ;
1E
b1 G
b1 -
b1 5
1+
#830000
b1111 =
b1111 &
b1111 3
b1111 I
b1111 )
b1111 4
b1111 J
b1111 <
0+
1!
#840000
b0 /
b0 6
0E
b11 G
b11 -
b11 5
b1111 :
b1111 9
b1111 ;
1+
#850000
0+
0!
#860000
b11 /
b11 6
b1100 ;
1E
1+
#870000
b1100 =
b1100 &
b1100 3
b1100 I
b1100 )
b1100 4
b1100 J
b1100 <
0+
1!
#880000
b10 /
b10 6
0E
b1100 :
b1100 9
b11 ;
1+
#890000
0+
0!
#900000
b1 /
b1 6
b1110 ;
1E
b0 G
b0 -
b0 5
1+
#910000
b1110 =
b1110 &
b1110 3
b1110 I
b1110 )
b1110 4
b1110 J
b1110 <
0+
1!
#920000
b10 /
b10 6
0E
b11 G
b11 -
b11 5
b1110 :
b1110 9
b1001 ;
1+
#930000
0+
0!
#940000
b1 /
b1 6
b110 ;
1E
b10 G
b10 -
b10 5
1+
#950000
b110 =
b110 &
b110 3
b110 I
b110 )
b110 4
b110 J
b110 <
0+
1!
#960000
b11 /
b11 6
0E
b1 G
b1 -
b1 5
b110 :
b110 9
b1001 ;
1+
#970000
0+
0!
#980000
b0 /
b0 6
b111 ;
1E
b10 G
b10 -
b10 5
1+
#990000
b111 =
b111 &
b111 3
b111 I
b111 )
b111 4
b111 J
b111 <
0+
1!
#1000000
b1 /
b1 6
0E
b1 G
b1 -
b1 5
b111 :
b111 9
b1100 ;
1+
#1010000
0+
0!
#1020000
b11 /
b11 6
b1 ;
1E
b11 G
b11 -
b11 5
1+
#1030000
b1 =
b1 &
b1 3
b1 I
b1 )
b1 4
b1 J
b1 <
0+
1!
#1040000
0E
b0 G
b0 -
b0 5
b1 :
b1 9
b111 ;
1+
#1050000
0+
0!
#1060000
b10 /
b10 6
b1111 ;
1E
b1 G
b1 -
b1 5
1+
#1070000
b1111 =
b1111 &
b1111 3
b1111 I
b1111 )
b1111 4
b1111 J
b1111 <
0+
1!
#1080000
b0 /
b0 6
0E
b11 G
b11 -
b11 5
b1111 :
b1111 9
b1110 ;
1+
#1090000
0+
0!
#1100000
b10 /
b10 6
b1000 ;
1E
1+
#1110000
b1000 =
b1000 &
b1000 3
b1000 I
b1000 )
b1000 4
b1000 J
b1000 <
0+
1!
#1120000
b1 /
b1 6
0E
b10 G
b10 -
b10 5
b1000 :
b1000 9
b10 ;
1+
#1130000
0+
0!
#1140000
b10 /
b10 6
b1001 ;
1E
b0 G
b0 -
b0 5
1+
#1150000
b1001 =
b1001 &
b1001 3
b1001 I
b1001 )
b1001 4
b1001 J
b1001 <
0+
1!
#1160000
b11 /
b11 6
0E
b10 G
b10 -
b10 5
b1001 :
b1001 9
b110 ;
1+
#1170000
0+
0!
#1180000
b0 /
b0 6
b1011 ;
1E
b1 G
b1 -
b1 5
1+
#1190000
b1011 =
b1011 &
b1011 3
b1011 I
b1011 )
b1011 4
b1011 J
b1011 <
0+
1!
#1200000
b11 /
b11 6
0E
b10 G
b10 -
b10 5
b1011 :
b1011 9
b1100 ;
1+
#1210000
0+
0!
#1220000
b0 /
b0 6
b11 ;
1E
b11 G
b11 -
b11 5
1+
#1230000
b11 =
b11 &
b11 3
b11 I
b11 )
b11 4
b11 J
b11 <
0+
1!
#1240000
b1 /
b1 6
0E
b0 G
b0 -
b0 5
b11 :
b11 9
b1100 ;
1+
#1250000
0+
0!
#1260000
b11 /
b11 6
b1 ;
1E
b11 G
b11 -
b11 5
1+
#1270000
b1 =
b1 &
b1 3
b1 I
b1 )
b1 4
b1 J
b1 <
0+
1!
#1280000
b1 /
b1 6
0E
b0 G
b0 -
b0 5
b1 :
b1 9
b111 ;
1+
#1290000
0+
0!
#1300000
b11 /
b11 6
b1101 ;
1E
b1 G
b1 -
b1 5
1+
#1310000
b1101 =
b1101 &
b1101 3
b1101 I
b1101 )
b1101 4
b1101 J
b1101 <
0+
1!
#1320000
b1 /
b1 6
0E
b11 G
b11 -
b11 5
b1101 :
b1101 9
b111 ;
1+
#1330000
0+
0!
#1340000
b1101 ;
1E
b1 G
b1 -
b1 5
1+
#1350000
0+
1!
#1360000
b10 /
b10 6
0E
b11 G
b11 -
b11 5
b101 ;
1+
#1370000
0+
0!
#1380000
b0 /
b0 6
b110 ;
1E
b1 G
b1 -
b1 5
1+
#1390000
b110 =
b110 &
b110 3
b110 I
b110 )
b110 4
b110 J
b110 <
0+
1!
#1400000
b1 /
b1 6
0E
b110 :
b110 9
b1000 ;
1+
#1410000
0+
0!
#1420000
b11 /
b11 6
b1 ;
1E
b10 G
b10 -
b10 5
1+
#1430000
b1 =
b1 &
b1 3
b1 I
b1 )
b1 4
b1 J
b1 <
0+
1!
#1440000
b1 /
b1 6
0E
b0 G
b0 -
b0 5
b1 :
b1 9
b111 ;
1+
#1450000
0+
0!
#1460000
b1101 ;
1E
b1 G
b1 -
b1 5
1+
#1470000
b1101 =
b1101 &
b1101 3
b1101 I
b1101 )
b1101 4
b1101 J
b1101 <
0+
1!
#1480000
b10 /
b10 6
0E
b11 G
b11 -
b11 5
b1101 :
b1101 9
b101 ;
1+
#1490000
0+
0!
#1500000
b11 /
b11 6
b110 ;
1E
b1 G
b1 -
b1 5
1+
#1510000
b110 =
b110 &
b110 3
b110 I
b110 )
b110 4
b110 J
b110 <
0+
1!
#1520000
b10 /
b10 6
0E
b110 :
b110 9
b1011 ;
1+
#1530000
0+
0!
#1540000
b1 /
b1 6
b1110 ;
1E
b10 G
b10 -
b10 5
1+
#1550000
b1110 =
b1110 &
b1110 3
b1110 I
b1110 )
b1110 4
b1110 J
b1110 <
0+
1!
#1560000
b11 /
b11 6
0E
b11 G
b11 -
b11 5
b1110 :
b1110 9
b1001 ;
1+
#1570000
0+
0!
#1580000
b111 ;
1E
b10 G
b10 -
b10 5
1+
#1590000
b111 =
b111 &
b111 3
b111 I
b111 )
b111 4
b111 J
b111 <
0+
1!
#1600000
b1 /
b1 6
0E
b1 G
b1 -
b1 5
b111 :
b111 9
b1111 ;
1+
#1610000
0+
0!
#1620000
b0 /
b0 6
b1101 ;
1E
b11 G
b11 -
b11 5
1+
#1630000
b1101 =
b1101 &
b1101 3
b1101 I
b1101 )
b1101 4
b1101 J
b1101 <
0+
1!
#1640000
b1 /
b1 6
0E
b1101 :
b1101 9
b100 ;
1+
#1650000
0+
0!
#1660000
b0 /
b0 6
b1 ;
1E
b1 G
b1 -
b1 5
1+
#1670000
b1 =
b1 &
b1 3
b1 I
b1 )
b1 4
b1 J
b1 <
0+
1!
#1680000
0E
b0 G
b0 -
b0 5
b1 :
b1 9
b100 ;
1+
#1690000
0+
0!
#1700000
b10 /
b10 6
b0 ;
1E
b1 G
b1 -
b1 5
1+
#1710000
b0 =
b0 &
b0 3
b0 I
b0 )
b0 4
b0 J
b0 <
0+
1!
#1720000
0E
b0 G
b0 -
b0 5
b0 :
b0 9
b10 ;
1+
#1730000
0+
0!
#1740000
b0 /
b0 6
b1010 ;
1E
1+
#1750000
b1010 =
b1010 &
b1010 3
b1010 I
b1010 )
b1010 4
b1010 J
b1010 <
0+
1!
#1760000
0E
b10 G
b10 -
b10 5
b1010 :
b1010 9
b1000 ;
1+
#1770000
0+
0!
#1780000
b10 /
b10 6
b0 ;
1E
1+
#1790000
b0 =
b0 &
b0 3
b0 I
b0 )
b0 4
b0 J
b0 <
0+
1!
#1800000
b1 /
b1 6
0E
b0 G
b0 -
b0 5
b0 :
b0 9
b10 ;
1+
#1810000
0+
0!
#1820000
b0 /
b0 6
b1001 ;
1E
1+
#1830000
b1001 =
b1001 &
b1001 3
b1001 I
b1001 )
b1001 4
b1001 J
b1001 <
0+
1!
#1840000
b11 /
b11 6
0E
b10 G
b10 -
b10 5
b1001 :
b1001 9
b100 ;
1+
#1850000
0+
0!
#1860000
b1 /
b1 6
b11 ;
1E
b1 G
b1 -
b1 5
1+
#1870000
b11 =
b11 &
b11 3
b11 I
b11 )
b11 4
b11 J
b11 <
0+
1!
#1880000
b11 /
b11 6
0E
b0 G
b0 -
b0 5
b11 :
b11 9
b1101 ;
1+
#1890000
0+
0!
#1900000
b1 /
b1 6
b111 ;
1E
b11 G
b11 -
b11 5
1+
#1910000
b111 =
b111 &
b111 3
b111 I
b111 )
b111 4
b111 J
b111 <
0+
1!
#1920000
b0 /
b0 6
0E
b1 G
b1 -
b1 5
b111 :
b111 9
b1101 ;
1+
#1930000
0+
0!
#1940000
b11 /
b11 6
b100 ;
1E
b11 G
b11 -
b11 5
1+
#1950000
b100 =
b100 &
b100 3
b100 I
b100 )
b100 4
b100 J
b100 <
0+
1!
#1960000
0E
b1 G
b1 -
b1 5
b100 :
b100 9
b11 ;
1+
#1970000
0+
0!
#1980000
b0 /
b0 6
b1111 ;
1E
b0 G
b0 -
b0 5
1+
#1990000
b1111 =
b1111 &
b1111 3
b1111 I
b1111 )
b1111 4
b1111 J
b1111 <
0+
1!
#2000000
0E
b11 G
b11 -
b11 5
b1111 :
b1111 9
b1100 ;
1+
#2010000
0+
0!
#2020000
b11 /
b11 6
b0 ;
1E
1+
#2030000
b0 =
b0 &
b0 3
b0 I
b0 )
b0 4
b0 J
b0 <
0+
1!
#2040000
0E
b0 G
b0 -
b0 5
b0 :
b0 9
b11 ;
1+
#2050000
0+
0!
#2060000
b10 /
b10 6
b1111 ;
1E
1+
#2070000
b1111 =
b1111 &
b1111 3
b1111 I
b1111 )
b1111 4
b1111 J
b1111 <
0+
1!
#2080000
b0 /
b0 6
0E
b11 G
b11 -
b11 5
b1111 :
b1111 9
b1110 ;
1+
#2090000
0+
0!
#2100000
b10 /
b10 6
b1000 ;
1E
1+
#2110000
b1000 =
b1000 &
b1000 3
b1000 I
b1000 )
b1000 4
b1000 J
b1000 <
0+
1!
#2120000
b1 /
b1 6
0E
b10 G
b10 -
b10 5
b1000 :
b1000 9
b10 ;
1+
#2130000
0+
0!
#2140000
b0 /
b0 6
b1001 ;
1E
b0 G
b0 -
b0 5
1+
#2150000
b1001 =
b1001 &
b1001 3
b1001 I
b1001 )
b1001 4
b1001 J
b1001 <
0+
1!
#2160000
b10 /
b10 6
0E
b10 G
b10 -
b10 5
b1001 :
b1001 9
b100 ;
1+
#2170000
0+
0!
#2180000
b0 /
b0 6
b10 ;
1E
b1 G
b1 -
b1 5
1+
#2190000
b10 =
b10 &
b10 3
b10 I
b10 )
b10 4
b10 J
b10 <
0+
1!
#2200000
b11 /
b11 6
0E
b0 G
b0 -
b0 5
b10 :
b10 9
b1000 ;
1+
#2210000
0+
0!
#2220000
b0 /
b0 6
b11 ;
1E
b10 G
b10 -
b10 5
1+
#2230000
b11 =
b11 &
b11 3
b11 I
b11 )
b11 4
b11 J
b11 <
0+
1!
#2240000
b10 /
b10 6
0E
b0 G
b0 -
b0 5
b11 :
b11 9
b1100 ;
1+
#2250000
0+
0!
#2260000
b10 ;
1E
b11 G
b11 -
b11 5
1+
#2270000
b10 =
b10 &
b10 3
b10 I
b10 )
b10 4
b10 J
b10 <
0+
1!
#2280000
0E
b0 G
b0 -
b0 5
b10 :
b10 9
b1010 ;
1+
#2290000
0+
0!
#2300000
b0 /
b0 6
b1010 ;
1E
b10 G
b10 -
b10 5
1+
#2310000
b1010 =
b1010 &
b1010 3
b1010 I
b1010 )
b1010 4
b1010 J
b1010 <
0+
1!
#2320000
0E
b1010 :
b1010 9
b1000 ;
1+
#2330000
0+
0!
#2340000
b11 /
b11 6
b0 ;
1E
1+
#2350000
b0 =
b0 &
b0 3
b0 I
b0 )
b0 4
b0 J
b0 <
0+
1!
#2360000
0E
b0 G
b0 -
b0 5
b0 :
b0 9
b11 ;
1+
#2370000
0+
0!
#2380000
b10 /
b10 6
b1111 ;
1E
1+
#2390000
b1111 =
b1111 &
b1111 3
b1111 I
b1111 )
b1111 4
b1111 J
b1111 <
0+
1!
#2400000
0E
b11 G
b11 -
b11 5
b1111 :
b1111 9
b1110 ;
1+
#2410000
0+
0!
#2420000
b1010 ;
1E
1+
#2430000
b1010 =
b1010 &
b1010 3
b1010 I
b1010 )
b1010 4
b1010 J
b1010 <
0+
1!
#2440000
0E
b10 G
b10 -
b10 5
b1010 :
b1010 9
b1010 ;
1+
#2450000
0+
0!
#2460000
b0 /
b0 6
b1010 ;
1E
1+
#2470000
0+
1!
#2480000
0E
b1000 ;
1+
#2490000
0+
0!
#2500000
b11 /
b11 6
b0 ;
1E
1+
#2510000
b0 =
b0 &
b0 3
b0 I
b0 )
b0 4
b0 J
b0 <
0+
1!
#2520000
0E
b0 G
b0 -
b0 5
b0 :
b0 9
b11 ;
1+
#2530000
0+
0!
#2540000
b10 /
b10 6
b1111 ;
1E
1+
#2550000
b1111 =
b1111 &
b1111 3
b1111 I
b1111 )
b1111 4
b1111 J
b1111 <
0+
1!
#2560000
0E
b11 G
b11 -
b11 5
b1111 :
b1111 9
b1110 ;
1+
#2570000
0+
0!
#2580000
b1 /
b1 6
b1010 ;
1E
1+
#2590000
b1010 =
b1010 &
b1010 3
b1010 I
b1010 )
b1010 4
b1010 J
b1010 <
0+
1!
#2600000
b11 /
b11 6
0E
b10 G
b10 -
b10 5
b1010 :
b1010 9
b1001 ;
1+
#2610000
0+
0!
#2620000
b0 /
b0 6
b111 ;
1E
1+
#2630000
b111 =
b111 &
b111 3
b111 I
b111 )
b111 4
b111 J
b111 <
0+
1!
#2640000
b10 /
b10 6
0E
b1 G
b1 -
b1 5
b111 :
b111 9
b1100 ;
1+
#2650000
0+
0!
#2660000
b1 /
b1 6
b10 ;
1E
b11 G
b11 -
b11 5
1+
#2670000
b10 =
b10 &
b10 3
b10 I
b10 )
b10 4
b10 J
b10 <
0+
1!
#2680000
b0 /
b0 6
0E
b0 G
b0 -
b0 5
b10 :
b10 9
b1001 ;
1+
#2690000
0+
0!
#2700000
b10 /
b10 6
b100 ;
1E
b10 G
b10 -
b10 5
1+
